nusex/__init__.py
nusex/__main__.py
nusex/constants.py
nusex/errors.py
nusex/helpers.py
nusex/profile.py
nusex/template.py
nusex/blueprints/__init__.py
nusex/blueprints/base.py
nusex/blueprints/generic.py
nusex/blueprints/python.py
nusex/blueprints/rust.py
nusex/cli/__init__.py
nusex/cli/cli.py
nusex/cli/commands/__init__.py
nusex/cli/commands/build.py
nusex/cli/commands/config.py
nusex/cli/commands/delete.py
nusex/cli/commands/deploy.py
nusex/cli/commands/download.py
nusex/cli/commands/init.py
nusex/cli/commands/list.py
nusex/cli/commands/migrate.py
nusex/cli/commands/profile.py
nusex/cli/commands/rename.py
nusex/spec/__init__.py
nusex/spec/nsc.py
nusex/spec/nsp.py
nusex/spec/nsx.py
nusex/utils/__init__.py
nusex/utils/downloader.py
nusex-1.3.0.dist-info/LICENSE
nusex-1.3.0.dist-info/METADATA
nusex-1.3.0.dist-info/WHEEL
nusex-1.3.0.dist-info/entry_points.txt
nusex-1.3.0.dist-info/top_level.txt
nusex-1.3.0.dist-info/RECORD
