Metadata-Version: 2.1
Name: nusex
Version: 1.3.0
Summary: A dynamic, multi-language project templating utility.
Home-page: https://github.com/nusex/nusex
Author: Ethan Henderson
Author-email: ethan.henderson.1998@gmail.com
License: BSD-3-Clause
Project-URL: Documentation, https://nusex.readthedocs.io/en/latest
Project-URL: Source, https://github.com/nusex/nusex
Project-URL: Bug Tracker, https://github.com/nusex/nusex/issues
Project-URL: CI, https://github.com/nusex/nusex/actions
Platform: UNKNOWN
Classifier: Development Status :: 5 - Production/Stable
Classifier: Environment :: Console
Classifier: Intended Audience :: Developers
Classifier: License :: OSI Approved :: BSD License
Classifier: Natural Language :: English
Classifier: Operating System :: MacOS
Classifier: Operating System :: Microsoft :: Windows
Classifier: Operating System :: OS Independent
Classifier: Operating System :: POSIX
Classifier: Operating System :: Unix
Classifier: Programming Language :: Python :: 3
Classifier: Programming Language :: Python :: 3 :: Only
Classifier: Programming Language :: Python :: 3.6
Classifier: Programming Language :: Python :: 3.7
Classifier: Programming Language :: Python :: 3.8
Classifier: Programming Language :: Python :: 3.9
Classifier: Programming Language :: Python :: 3.10
Classifier: Programming Language :: Python :: Implementation :: CPython
Classifier: Programming Language :: Python :: Implementation :: PyPy
Classifier: Topic :: Software Development
Classifier: Topic :: Software Development :: Code Generators
Classifier: Topic :: Utilities
Requires-Python: >=3.6.0,<3.12
License-File: LICENSE
